my_own_package/__init__.py
george_pack1-0.1.0.dist-info/METADATA
george_pack1-0.1.0.dist-info/WHEEL
george_pack1-0.1.0.dist-info/top_level.txt
george_pack1-0.1.0.dist-info/RECORD
