Metadata-Version: 2.1
Name: george-pack1
Version: 0.1.0
Summary: This is my tutorial
Author: Herescu George
Author-email: hergeo8@gmail.com
License: UNKNOWN
Platform: UNKNOWN
